mhca/__init__.py
mhca/__main__.py
mhca/annotate_haplotype.py
mhca/check_CDS.py
mhca/genbank2fullfasta.py
mhca/refseq2fullfasta.py
mhca/update_feature_table.py
mhca/data/LRG_RefSeqGene.tsv
mhca/data/__init__.py
mhca/data/gene_pseudogene.tsv
mhca/data/genes_pseudogenes.tsv
mhca/data/imgt_alleles.tar.gz
mhca/data/refseqgene.all.MHC.full_n.fasta
mhca/data/rs38.fasta.gz
mhca/data/rs38_transcripts.tar.gz
mhca/data/rsg_transcripts.tar.gz
MHC_Annotation-0.1.1.dist-info/LICENSE
MHC_Annotation-0.1.1.dist-info/METADATA
MHC_Annotation-0.1.1.dist-info/WHEEL
MHC_Annotation-0.1.1.dist-info/entry_points.txt
MHC_Annotation-0.1.1.dist-info/top_level.txt
MHC_Annotation-0.1.1.dist-info/RECORD
