Metadata-Version: 2.1
Name: MHC-Annotation
Version: 0.1.1
Summary: UNKNOWN
Home-page: https://github.com/DiltheyLab/MHC-annotation
Author: Torsten Houwaart
Author-email: houwaart@hhu.de
License: MIT
Platform: UNKNOWN
Requires-Python: >=3.7
